pyQuASAR_genotype/__init__.py
pyQuASAR_genotype/genotype.py
pyQuASAR_genotype-0.1.30.dist-info/LICENSE
pyQuASAR_genotype-0.1.30.dist-info/METADATA
pyQuASAR_genotype-0.1.30.dist-info/WHEEL
pyQuASAR_genotype-0.1.30.dist-info/entry_points.txt
pyQuASAR_genotype-0.1.30.dist-info/top_level.txt
pyQuASAR_genotype-0.1.30.dist-info/RECORD
