Metadata-Version: 2.1
Name: pyQuASAR-genotype
Version: 0.1.30
Summary: Command line tool for genotyping with QuASAR
Home-page: https://gitlab.com/aaylward/pyQuASAR_genotype
Author: Anthony Aylward
Author-email: aaylward@salk.edu
License: UNKNOWN
Platform: UNKNOWN
Classifier: Programming Language :: Python :: 3
Classifier: License :: OSI Approved :: MIT License
Classifier: Operating System :: OS Independent
License-File: LICENSE
Requires-Dist: pyQuASAR
Requires-Dist: seqalign
Requires-Dist: wasp-map
